pricecypher/__init__.py
pricecypher/config_sections.py
pricecypher/datasets.py
pricecypher/exceptions.py
pricecypher/rest.py
pricecypher/script_service.py
pricecypher/collections/__init__.py
pricecypher/collections/base_collection.py
pricecypher/collections/scope_collection.py
pricecypher/collections/scope_value_collection.py
pricecypher/contracts/__init__.py
pricecypher/contracts/pricecypher_model.py
pricecypher/contracts/handlers/__init__.py
pricecypher/contracts/handlers/base_handler.py
pricecypher/contracts/handlers/batch_inference_handler.py
pricecypher/contracts/handlers/data_report_handler.py
pricecypher/contracts/handlers/df_handler.py
pricecypher/contracts/handlers/inference_handler.py
pricecypher/contracts/handlers/read_parquet_handler.py
pricecypher/contracts/handlers/read_string_handler.py
pricecypher/contracts/handlers/train_models_handler.py
pricecypher/contracts/handlers/write_parquet_handler.py
pricecypher/contracts/handlers/write_string_handler.py
pricecypher/contracts/scripts/__init__.py
pricecypher/contracts/scripts/quality_test_script.py
pricecypher/contracts/scripts/scope_script.py
pricecypher/contracts/scripts/script.py
pricecypher/dataclasses/__init__.py
pricecypher/dataclasses/dataclass_protocol.py
pricecypher/dataclasses/predict_result.py
pricecypher/dataclasses/response.py
pricecypher/dataclasses/test_result.py
pricecypher/dataclasses/settings/__init__.py
pricecypher/dataclasses/settings/azure_blob_settings.py
pricecypher/dataclasses/settings/handler_settings.py
pricecypher/dataclasses/settings/remote_storage_settings.py
pricecypher/encoders/__init__.py
pricecypher/encoders/json_encoder.py
pricecypher/endpoints/__init__.py
pricecypher/endpoints/base_endpoint.py
pricecypher/endpoints/config.py
pricecypher/endpoints/datasets.py
pricecypher/endpoints/scripts.py
pricecypher/endpoints/users.py
pricecypher/enums/__init__.py
pricecypher/enums/access_token_grant_type.py
pricecypher/enums/accuracy.py
pricecypher/enums/scripts.py
pricecypher_sdk-3.5.1.dist-info/LICENSE
pricecypher_sdk-3.5.1.dist-info/METADATA
pricecypher_sdk-3.5.1.dist-info/WHEEL
pricecypher_sdk-3.5.1.dist-info/entry_points.txt
pricecypher_sdk-3.5.1.dist-info/pbr.json
pricecypher_sdk-3.5.1.dist-info/top_level.txt
pricecypher_sdk-3.5.1.dist-info/RECORD
