Metadata-Version: 2.1
Name: pricecypher-sdk
Version: 3.5.1
Summary: Python wrapper around the different PriceCypher APIs
Home-page: https://github.com/marketredesign/pricecypher_python_sdk
Author: Deloitte Consulting B.V.
Project-URL: Bug Tracker, https://github.com/marketredesign/pricecypher_python_sdk/issues
Classifier: Programming Language :: Python :: 3
Classifier: License :: OSI Approved :: MIT License
Classifier: Operating System :: OS Independent
Requires-Python: >=3.9
License-File: LICENSE
Requires-Dist: azure-identity~=1.17
Requires-Dist: better-abc>=0.0.3
Requires-Dist: marshmallow-dataclass~=8.5
Requires-Dist: mlflow~=2.18
Requires-Dist: numpy>=1.18
Requires-Dist: oic~=1.7
Requires-Dist: pandas>=1.4
Requires-Dist: pbr~=6.0
Requires-Dist: pyarrow~=17.0
Requires-Dist: requests~=2.14
Requires-Dist: smart_open[azure,s3]~=7.0
Provides-Extra: testing
Requires-Dist: mock>=1.3.0; extra == "testing"
